openapi_schema_pydantic/__init__.py
openapi_schema_pydantic/py.typed
openapi_schema_pydantic/util.py
openapi_schema_pydantic/v3/__init__.py
openapi_schema_pydantic/v3/v3_0_3/__init__.py
openapi_schema_pydantic/v3/v3_0_3/callback.py
openapi_schema_pydantic/v3/v3_0_3/components.py
openapi_schema_pydantic/v3/v3_0_3/contact.py
openapi_schema_pydantic/v3/v3_0_3/discriminator.py
openapi_schema_pydantic/v3/v3_0_3/encoding.py
openapi_schema_pydantic/v3/v3_0_3/example.py
openapi_schema_pydantic/v3/v3_0_3/external_documentation.py
openapi_schema_pydantic/v3/v3_0_3/header.py
openapi_schema_pydantic/v3/v3_0_3/info.py
openapi_schema_pydantic/v3/v3_0_3/license.py
openapi_schema_pydantic/v3/v3_0_3/link.py
openapi_schema_pydantic/v3/v3_0_3/media_type.py
openapi_schema_pydantic/v3/v3_0_3/oauth_flow.py
openapi_schema_pydantic/v3/v3_0_3/oauth_flows.py
openapi_schema_pydantic/v3/v3_0_3/open_api.py
openapi_schema_pydantic/v3/v3_0_3/operation.py
openapi_schema_pydantic/v3/v3_0_3/parameter.py
openapi_schema_pydantic/v3/v3_0_3/path_item.py
openapi_schema_pydantic/v3/v3_0_3/paths.py
openapi_schema_pydantic/v3/v3_0_3/reference.py
openapi_schema_pydantic/v3/v3_0_3/request_body.py
openapi_schema_pydantic/v3/v3_0_3/response.py
openapi_schema_pydantic/v3/v3_0_3/responses.py
openapi_schema_pydantic/v3/v3_0_3/schema.py
openapi_schema_pydantic/v3/v3_0_3/security_requirement.py
openapi_schema_pydantic/v3/v3_0_3/security_scheme.py
openapi_schema_pydantic/v3/v3_0_3/server.py
openapi_schema_pydantic/v3/v3_0_3/server_variable.py
openapi_schema_pydantic/v3/v3_0_3/tag.py
openapi_schema_pydantic/v3/v3_0_3/util.py
openapi_schema_pydantic/v3/v3_0_3/xml.py
openapi_schema_pydantic/v3/v3_1_0/__init__.py
openapi_schema_pydantic/v3/v3_1_0/callback.py
openapi_schema_pydantic/v3/v3_1_0/components.py
openapi_schema_pydantic/v3/v3_1_0/contact.py
openapi_schema_pydantic/v3/v3_1_0/discriminator.py
openapi_schema_pydantic/v3/v3_1_0/encoding.py
openapi_schema_pydantic/v3/v3_1_0/example.py
openapi_schema_pydantic-1.2.4.dist-info/LICENSE
openapi_schema_pydantic-1.2.4.dist-info/METADATA
openapi_schema_pydantic-1.2.4.dist-info/WHEEL
openapi_schema_pydantic-1.2.4.dist-info/top_level.txt
openapi_schema_pydantic-1.2.4.dist-info/RECORD
