Metadata-Version: 2.1
Name: openapi-schema-pydantic
Version: 1.2.4
Summary: OpenAPI (v3) specification schema as pydantic class
Home-page: https://github.com/kuimono/openapi-schema-pydantic
Author: Kuimono
Classifier: Programming Language :: Python :: 3
Classifier: License :: OSI Approved :: MIT License
Classifier: Operating System :: OS Independent
Requires-Python: >=3.6.1
License-File: LICENSE
